COPYING
MANIFEST.in
README.rst
buildout.cfg
requirements.txt
setup.py
version.txt
bob/__init__.py
bob.db.brsu.egg-info/PKG-INFO
bob.db.brsu.egg-info/SOURCES.txt
bob.db.brsu.egg-info/dependency_links.txt
bob.db.brsu.egg-info/entry_points.txt
bob.db.brsu.egg-info/not-zip-safe
bob.db.brsu.egg-info/requires.txt
bob.db.brsu.egg-info/top_level.txt
bob/db/__init__.py
bob/db/brsu/__init__.py
bob/db/brsu/create.py
bob/db/brsu/driver.py
bob/db/brsu/models.py
bob/db/brsu/query.py
bob/db/brsu/test.py
doc/guide.rst
doc/index.rst
doc/links.rst
doc/py_api.rst
doc/img/bob-128x128.png
doc/img/bob-favicon.ico
doc/img/bob-logo.png