Metadata-Version: 1.1
Name: bob.db.brsu
Version: 0.0.1
Summary: Bob's interface for the BRSU Multispectral Face/Skin Database
Home-page: https://gitlab.idiap.ch/bob/bob.db.brsu
Author: Guillaume Heusch
Author-email: guillaume.heusch@idiap.ch
License: GPLv3
Keywords: bob
Platform: UNKNOWN
Classifier: Framework :: Bob
Classifier: Development Status :: 4 - Beta
Classifier: Intended Audience :: Science/Research
Classifier: License :: OSI Approved :: GNU General Public License v3 (GPLv3)
Classifier: Natural Language :: English
Classifier: Programming Language :: Python
Classifier: Programming Language :: Python :: 3
Classifier: Topic :: Scientific/Engineering :: Artificial Intelligence
Classifier: Topic :: Software Development :: Libraries :: Python Modules
